odoo/addons/stock_location_bin_name/README.rst
odoo/addons/stock_location_bin_name/__init__.py
odoo/addons/stock_location_bin_name/__manifest__.py
odoo/addons/stock_location_bin_name/i18n/stock_location_bin_name.pot
odoo/addons/stock_location_bin_name/models/__init__.py
odoo/addons/stock_location_bin_name/models/stock_location.py
odoo/addons/stock_location_bin_name/readme/CONTRIBUTORS.rst
odoo/addons/stock_location_bin_name/readme/CREDITS.rst
odoo/addons/stock_location_bin_name/readme/DESCRIPTION.rst
odoo/addons/stock_location_bin_name/static/description/icon.png
odoo/addons/stock_location_bin_name/static/description/index.html
odoo/addons/stock_location_bin_name/views/stock_location.xml
odoo14_addon_stock_location_bin_name-14.0.1.0.1.dist-info/METADATA
odoo14_addon_stock_location_bin_name-14.0.1.0.1.dist-info/WHEEL
odoo14_addon_stock_location_bin_name-14.0.1.0.1.dist-info/top_level.txt
odoo14_addon_stock_location_bin_name-14.0.1.0.1.dist-info/RECORD
